<?xml version="1.0" ?>
<annotation>
<folder>JPEGImages</folder>
<filename>28.jpg</filename>
<path>D:\desktop\MidAutumn\JPEGImages\28.jpg</path>
<source>
    <database>Unknown</database>
</source>
<size>
    <width>500</width>
    <height>375</height>
    <depth>3</depth>
</size>

<segmented>0</segmented>
    <object>
    <name>MoonCake</name>
    <pose>Unspecified</pose>
    <truncated>0</truncated>
    <difficult>0</difficult>
    <bndbox>
        <xmin>115</xmin>
        <ymin>62</ymin>
        <xmax>209</xmax>
        <ymax>152</ymax>
    </bndbox>
</object>
    <object>
    <name>MoonCake</name>
    <pose>Unspecified</pose>
    <truncated>0</truncated>
    <difficult>0</difficult>
    <bndbox>
        <xmin>207</xmin>
        <ymin>42</ymin>
        <xmax>295</xmax>
        <ymax>136</ymax>
    </bndbox>
</object>
    <object>
    <name>MoonCake</name>
    <pose>Unspecified</pose>
    <truncated>0</truncated>
    <difficult>0</difficult>
    <bndbox>
        <xmin>283</xmin>
        <ymin>90</ymin>
        <xmax>371</xmax>
        <ymax>176</ymax>
    </bndbox>
</object>
    <object>
    <name>MoonCake</name>
    <pose>Unspecified</pose>
    <truncated>0</truncated>
    <difficult>0</difficult>
    <bndbox>
        <xmin>287</xmin>
        <ymin>174</ymin>
        <xmax>379</xmax>
        <ymax>268</ymax>
    </bndbox>
</object>
    <object>
    <name>MoonCake</name>
    <pose>Unspecified</pose>
    <truncated>0</truncated>
    <difficult>0</difficult>
    <bndbox>
        <xmin>225</xmin>
        <ymin>242</ymin>
        <xmax>313</xmax>
        <ymax>334</ymax>
    </bndbox>
</object>
    <object>
    <name>MoonCake</name>
    <pose>Unspecified</pose>
    <truncated>0</truncated>
    <difficult>0</difficult>
    <bndbox>
        <xmin>131</xmin>
        <ymin>232</ymin>
        <xmax>221</xmax>
        <ymax>332</ymax>
    </bndbox>
</object>
    <object>
    <name>MoonCake</name>
    <pose>Unspecified</pose>
    <truncated>0</truncated>
    <difficult>0</difficult>
    <bndbox>
        <xmin>91</xmin>
        <ymin>150</ymin>
        <xmax>189</xmax>
        <ymax>238</ymax>
    </bndbox>
</object>
</annotation>
