<?xml version="1.0" ?>
<annotation>
<folder>JPEGImages</folder>
<filename>55.jpg</filename>
<path>D:\desktop\MidAutumn\JPEGImages\55.jpg</path>
<source>
    <database>Unknown</database>
</source>
<size>
    <width>500</width>
    <height>500</height>
    <depth>3</depth>
</size>

<segmented>0</segmented>
    <object>
    <name>MoonCake</name>
    <pose>Unspecified</pose>
    <truncated>0</truncated>
    <difficult>0</difficult>
    <bndbox>
        <xmin>41</xmin>
        <ymin>151</ymin>
        <xmax>207</xmax>
        <ymax>319</ymax>
    </bndbox>
</object>
    <object>
    <name>MoonCake</name>
    <pose>Unspecified</pose>
    <truncated>0</truncated>
    <difficult>0</difficult>
    <bndbox>
        <xmin>279</xmin>
        <ymin>139</ymin>
        <xmax>457</xmax>
        <ymax>307</ymax>
    </bndbox>
</object>
</annotation>
